README.md
pyproject.toml
src/fax/__init__.py
src/fax/api.py
src/fax/api_test.py
src/fax/impls.py
src/fax/impls_sharding_test.py
src/fax/impls_test.py
src/fax/primitives.py
src/fax/primitives_test.py
src/google_fax.egg-info/PKG-INFO
src/google_fax.egg-info/SOURCES.txt
src/google_fax.egg-info/dependency_links.txt
src/google_fax.egg-info/requires.txt
src/google_fax.egg-info/top_level.txt