Metadata-Version: 2.1
Name: google-fax
Version: 0.0.2
Summary: FAX is an implementation of federated operations using Jax primitives.
Author-email: Keith Rush <krush@google.com>, Zachary Charles <zachcharles@google.com>, Zachary Garrett <zachgarrett@google.com>
License: Apache-2.0
Project-URL: Repository, https://github.com/google-research/google-research
Keywords: federated,machine,learning,jax
Requires-Python: >=3.9
Requires-Dist: absl-py~=1.0
Requires-Dist: jax~=0.4.24
Requires-Dist: jaxlib~=0.4.24
